benchmark_data/get_chains.py
benchmark_data/get_updated_mmcifs.py
cluster_conformers/__init__.py
cluster_conformers/cluster_chains.py
cluster_conformers/cluster_monomers.py
cluster_conformers/distance_differences.py
cluster_conformers/get_cluster_results.py
cluster_conformers/utils/__init__.py
cluster_conformers/utils/appearance_utils.py
cluster_conformers/utils/db_utils.py
cluster_conformers/utils/download_utils.py
cluster_conformers/utils/io_utils.py
cluster_conformers/utils/linear_algebra_utils.py
cluster_conformers/utils/logging_utils.py
cluster_conformers/utils/parsing_utils.py
doc/source/conf.py
tests/__init__.py
tests/test_case.py
tests/test_cluster_chains.py
tests/test_cluster_monomers.py
tests/test_distance_differences.py
tests/test_download_utils.py
tests/test_io_utils.py
tests/test_linear_algebra.py
tests/test_parsing_utils.py
protein_cluster_conformers-1.2.1.dist-info/LICENSE
protein_cluster_conformers-1.2.1.dist-info/METADATA
protein_cluster_conformers-1.2.1.dist-info/WHEEL
protein_cluster_conformers-1.2.1.dist-info/entry_points.txt
protein_cluster_conformers-1.2.1.dist-info/top_level.txt
protein_cluster_conformers-1.2.1.dist-info/RECORD
