Metadata-Version: 2.1
Name: protein-cluster-conformers
Version: 1.2.1
Summary: Clusters conformations of monomeric protein
Home-page: https://github.com/PDBeurope/protein-cluster-conformers
Author: Joseph I. J. Ellaway
Author-email: jellaway@ebi.ac.uk
Keywords: cluster,monomeric,superpose,linear algebra,distance
Classifier: Development Status :: 5 - Production/Stable
Classifier: Intended Audience :: Science/Research
Classifier: Intended Audience :: Developers
Classifier: Programming Language :: Python :: 3.7
Classifier: Programming Language :: Python :: 3.8
Classifier: Programming Language :: Python :: 3.9
Classifier: Programming Language :: Python :: 3.10
Requires-Python: >=3.10
License-File: LICENSE
Requires-Dist: requests
Requires-Dist: numpy
Requires-Dist: pandas
Requires-Dist: pathlib
Requires-Dist: gemmi
Requires-Dist: scipy
Requires-Dist: scikit-learn
Requires-Dist: seaborn
Requires-Dist: matplotlib
Requires-Dist: argparse
Provides-Extra: test
Requires-Dist: pytest; extra == "test"
